csv2seed/__init__.py
csv2seed/cli.py
csv2seed/converter.py
csv2seed-0.2.0.dist-info/LICENSE
csv2seed-0.2.0.dist-info/METADATA
csv2seed-0.2.0.dist-info/WHEEL
csv2seed-0.2.0.dist-info/entry_points.txt
csv2seed-0.2.0.dist-info/top_level.txt
csv2seed-0.2.0.dist-info/RECORD
