Metadata-Version: 2.1
Name: csv2seed
Version: 0.2.0
Summary: CSV file converter to Laravel Seeders
Home-page: https://github.com/ErickTucto/csv2seed
Author: Erick Tucto
Author-email: erick.tucto@outlook.com
License: MIT
Keywords: csv,laravel,seeders,seed,converter,generator
Platform: UNKNOWN
